LICENSE
MANIFEST.in
README.rst
setup.cfg
setup.py
versioneer.py
solstice/__init__.py
solstice/config/__init__.py
solstice/config/__version__.py
solstice/config/_version.py
solstice/config/development/artellapipe-assets.yml
solstice/config/development/artellapipe-files.yml
solstice/config/development/artellapipe-launcher-plugins-dccselector.yml
solstice/config/development/artellapipe-launcher.yml
solstice/config/development/artellapipe-libs-drive.yml
solstice/config/development/artellapipe-libs-kitsu.yml
solstice/config/development/artellapipe-libs-naming.yml
solstice/config/development/artellapipe-media.yml
solstice/config/development/artellapipe-playblasts.yml
solstice/config/development/artellapipe-project.yml
solstice/config/development/artellapipe-pyblishplugins.yml
solstice/config/development/artellapipe-sequences.yml
solstice/config/development/artellapipe-shaders.yml
solstice/config/development/artellapipe-shots.yml
solstice/config/development/artellapipe-tags.yml
solstice/config/development/artellapipe-tools-alembicmanager.yml
solstice/config/development/artellapipe-tools-artellamanager.yml
solstice/config/development/artellapipe-tools-artellauploader.yml
solstice/config/development/artellapipe-tools-assetslibrary.yml
solstice/config/development/artellapipe-tools-assetsmanager.yml
solstice/config/development/artellapipe-tools-assetspublisher.yml
solstice/config/development/artellapipe-tools-breakdown.yml
solstice/config/development/artellapipe-tools-bugtracker.yml
solstice/config/development/artellapipe-tools-changelog.yml
solstice/config/development/artellapipe-tools-dependenciesmanager.yml
solstice/config/development/artellapipe-tools-lightrigsmanager.yml
solstice/config/development/artellapipe-tools-modelchecker.yml
solstice/config/development/artellapipe-tools-namemanager.yml
solstice/config/development/artellapipe-tools-playblastmanager.yml
solstice/config/development/artellapipe-tools-renamer.yml
solstice_config.egg-info/PKG-INFO
solstice_config.egg-info/SOURCES.txt
solstice_config.egg-info/dependency_links.txt
solstice_config.egg-info/not-zip-safe
solstice_config.egg-info/requires.txt
solstice_config.egg-info/top_level.txt
