Metadata-Version: 2.1
Name: solstice-config
Version: 0.0.23
Summary: Solstice Module that contains project-specific configuration files
Home-page: https://github.com/Solstice-Short-Film/solstice-config
Author: Tomas Poveda
Author-email: tpovedatd@gmail.com
License: MIT
Platform: UNKNOWN
Provides-Extra: dev
Provides-Extra: test
